{
  "isPage": false,
  "date": "2026-03-06T00:00:00.000Z",
  "movement": "Chest Press",
  "weight": "105 kg",
  "reps": "4",
  "notes": "Iso-Lateral",
  "body": {
    "raw": "",
    "code": "var Component=(()=>{var f=Object.create;var s=Object.defineProperty;var _=Object.getOwnPropertyDescriptor;var d=Object.getOwnPropertyNames;var g=Object.getPrototypeOf,p=Object.prototype.hasOwnProperty;var h=(t,e)=>()=>(e||t((e={exports:{}}).exports,e),e.exports),j=(t,e)=>{for(var n in e)s(t,n,{get:e[n],enumerable:!0})},m=(t,e,n,a)=>{if(e&&typeof e==\"object\"||typeof e==\"function\")for(let o of d(e))!p.call(t,o)&&o!==n&&s(t,o,{get:()=>e[o],enumerable:!(a=_(e,o))||a.enumerable});return t};var l=(t,e,n)=>(n=t!=null?f(g(t)):{},m(e||!t||!t.__esModule?s(n,\"default\",{value:t,enumerable:!0}):n,t)),C=t=>m(s({},\"__esModule\",{value:!0}),t);var u=h((F,c)=>{c.exports=_jsx_runtime});var w={};j(w,{default:()=>i,frontmatter:()=>M});var r=l(u()),M={date:\"2026-03-06\",movement:\"Chest Press\",weight:\"105 kg\",reps:\"4\",notes:\"Iso-Lateral\"};function x(t){return(0,r.jsx)(r.Fragment,{})}function i(t={}){let{wrapper:e}=t.components||{};return e?(0,r.jsx)(e,{...t,children:(0,r.jsx)(x,{...t})}):x(t)}return C(w);})();\n;return Component;"
  },
  "_id": "health/performance/chest-press-machine.md",
  "_raw": {
    "sourceFilePath": "health/performance/chest-press-machine.md",
    "sourceFileName": "chest-press-machine.md",
    "sourceFileDir": "health/performance",
    "contentType": "markdown",
    "flattenedPath": "health/performance/chest-press-machine"
  },
  "type": "Health",
  "readingTime": {
    "text": "0 min read",
    "minutes": 0,
    "time": 0,
    "words": 0
  },
  "slug": "performance/chest-press-machine",
  "path": "health/performance/chest-press-machine",
  "filePath": "health/performance/chest-press-machine.md",
  "toc": []
}